[
  {"date":"2026-07-19","category":"Moonbase","repository":"other","module":"","version":"","commit":"037f3a4513bd3f4c8608e6ef5bdc9c90f6f54b02","title":"llvm: add a patch form Arch Linux","summary":"llvm: add a patch form Arch Linux"},
  {"date":"2026-07-19","category":"Moonbase","repository":"other","module":"","version":"","commit":"2033a5ae86ec17da7c12e5bf03623e2172e58b60","title":"ruby: version bumed to 6.0.6","summary":"ruby: version bumed to 6.0.6"},
  {"date":"2026-07-19","category":"Moonbase","repository":"other","module":"","version":"","commit":"280c5acfeb87b475c78db5392279155950c24e21","title":"aalib: remove gcc/c23 fix about a gpm call in aacurkbd.c","summary":"aalib: remove gcc/c23 fix about a gpm call in aacurkbd.c"},
  {"date":"2026-07-19","category":"Moonbase","repository":"other","module":"cargo-c","version":"0.10.24","commit":"7653584b87ed8695cdd2a6ee30de529b53bca52e","title":"cargo-c updated to 0.10.24","summary":"version bumped to 0.10.24"},
  {"date":"2026-07-19","category":"Moonbase","repository":"other","module":"libpqxx","version":"8.0.2.","commit":"79a4217d8caa99814d35f31c4aeff0258a1b707d","title":"libpqxx updated to 8.0.2.","summary":"bump to 8.0.2."},
  {"date":"2026-07-19","category":"Moonbase","repository":"other","module":"freerdp","version":"3.30.0","commit":"831131c4bac18c561975f89e723c1f38b80000da","title":"freerdp updated to 3.30.0","summary":"version bumped to 3.30.0"},
  {"date":"2026-07-19","category":"Moonbase","repository":"other","module":"nss","version":"3.126","commit":"c073693ed6ee86dc5cd3b40801ecefc2858d8901","title":"nss updated to 3.126","summary":"version bumped to 3.126"},
  {"date":"2026-07-19","category":"Moonbase","repository":"other","module":"lighttpd","version":"1.4.85","commit":"f486ce804ada89e62813e4be975b25b0f87ee4e5","title":"lighttpd updated to 1.4.85","summary":"version bumped to 1.4.85"},
  {"date":"2026-07-19","category":"Moonbase","repository":"other","module":"","version":"","commit":"f5b235e634a096f791290f4213d1118470d8c00a","title":"iana-etc: refresh hash","summary":"iana-etc: refresh hash"},
  {"date":"2026-07-19","category":"Moonbase","repository":"other","module":"screen","version":"5.0.2","commit":"fc0aaa8a8079a4f8a8be135ad795da7ce3a1cc73","title":"screen updated to 5.0.2","summary":"version bumped to 5.0.2"},
  {"date":"2026-07-19","category":"Moonbase","repository":"xorg","module":"mesa-lib","version":"26.1.5","commit":"bdfc6776e663abcf1fc2d085e8020f0bfbb54b87","title":"mesa-lib updated to 26.1.5","summary":"version bumped to 26.1.5"},
  {"date":"2026-07-19","category":"Moonbase","repository":"core","module":"openssh","version":"10.4p1","commit":"0ad229b79dfe9da826673391492049a23e18635e","title":"openssh updated to 10.4p1","summary":"version bumped to 10.4p1"}
]
